wrapper_base/__init__.py
wrapper_base/base.py
wrapper_base-0.1.0.dist-info/METADATA
wrapper_base-0.1.0.dist-info/WHEEL
wrapper_base-0.1.0.dist-info/top_level.txt
wrapper_base-0.1.0.dist-info/RECORD
