Metadata-Version: 2.1
Name: wrapper-base
Version: 0.1.0
Summary: Base classes for an API Wrapper
Home-page: UNKNOWN
Author: Sunney-X
Author-email: sanishubitidze@live.com
License: UNKNOWN
Platform: UNKNOWN
